core/__init__.py
core/data_loader.py
core/equipment_config.py
core/health_scorer.py
core/report_generator.py
core/signal_processor.py
equipment/__init__.py
equipment/base_equipment.py
equipment/battery.py
equipment/inverter.py
equipment/solar_panel.py
utils/__init__.py
utils/validation.py
utils/visualization.py
pv_diagnostix_su-0.1.3.dist-info/METADATA
pv_diagnostix_su-0.1.3.dist-info/WHEEL
pv_diagnostix_su-0.1.3.dist-info/top_level.txt
pv_diagnostix_su-0.1.3.dist-info/RECORD
