Metadata-Version: 2.4
Name: PV-Diagnostix-Su
Version: 0.1.3
Requires-Python: >=3.8
Requires-Dist: pandas>=1.3.0
Requires-Dist: numpy>=1.21.0
Requires-Dist: scipy>=1.7.0
Requires-Dist: scikit-learn>=1.0.0
Requires-Dist: plotly>=5.0.0
Requires-Dist: pathlib
Requires-Dist: logging
Requires-Dist: PyYAML>=6.0
Requires-Dist: pywavelets
Dynamic: description
Dynamic: description-content-type
Dynamic: requires-dist
Dynamic: requires-python
